cid/__init__.py
cid/apps.py
cid/context_processors.py
cid/cursor.py
cid/log.py
cid/middleware.py
cid/models.py
cid/backends/__init__.py
cid/backends/mysql/__init__.py
cid/backends/mysql/base.py
cid/backends/oracle/__init__.py
cid/backends/oracle/base.py
cid/backends/postgis/__init__.py
cid/backends/postgis/base.py
cid/backends/postgresql/__init__.py
cid/backends/postgresql/base.py
cid/backends/sqlite3/__init__.py
cid/backends/sqlite3/base.py
cid/locals/__init__.py
cid/locals/base.py
cid/locals/context.py
django_cid-3.0.dist-info/METADATA
django_cid-3.0.dist-info/WHEEL
django_cid-3.0.dist-info/top_level.txt
django_cid-3.0.dist-info/RECORD
