Metadata-Version: 2.1
Name: django-cid
Version: 3.0
Summary: Correlation IDs in Django for debugging requests
Home-page: https://django-correlation-id.readthedocs.io/
Author: Snowball One
Author-email: opensource+django-cid@polyconseil.fr
Maintainer: Polyconseil
Maintainer-email: opensource+django-cid@polyconseil.fr
License: BSD-3-Clause
Project-URL: Documentation, https://django-correlation-id.readthedocs.io/
Project-URL: Source, https://github.com/Polyconseil/django-cid
Project-URL: Bug Tracker, https://github.com/Polyconseil/django-cid/issues
Project-URL: Changelog, https://django-correlation-id.readthedocs.io/en/latest/history.html
Keywords: django logging correlation id debugging
Platform: any
Classifier: Development Status :: 5 - Production/Stable
Classifier: Framework :: Django
Classifier: Framework :: Django :: 3
Classifier: Framework :: Django :: 3.1
Classifier: Framework :: Django :: 3.2
Classifier: Framework :: Django :: 4
Classifier: Framework :: Django :: 4.0
Classifier: Framework :: Django :: 4.1
Classifier: Framework :: Django :: 4.2
Classifier: Intended Audience :: Developers
Classifier: License :: OSI Approved :: BSD License
Classifier: Natural Language :: English
Classifier: Programming Language :: Python
Classifier: Programming Language :: Python :: 3
Classifier: Programming Language :: Python :: 3 :: Only
Classifier: Programming Language :: Python :: 3.8
Classifier: Programming Language :: Python :: 3.9
Classifier: Programming Language :: Python :: 3.10
Classifier: Programming Language :: Python :: 3.11
Requires-Python: >=3.8
Requires-Dist: django >=3.1
